<?xml version="1.0" encoding="utf-8"?>
<prefabs>
  <!-- Everything is categorized as 'Structure' unless explicitly categorized otherwise -->
  <!-- OUTPOST BACKGROUND WALLS -->
  <OpDeco name="" identifier="tsm_slogan1" subcategory="tsmmissions" nameidentifier="tsm_slogan" width="789" height="1123" scale="0.5" noninteractable="true" category="Decorative">
    <sprite texture="%ModDir%/map/slogan1.png" sourcerect="0,0,789,1123" depth="0.97" premultiplyalpha="false" origin="0.5,0.5" />
  </OpDeco>
  <OpDeco name="" identifier="tsm_signboard1" subcategory="tsmmissions" nameidentifier="tsm_slogan" width="1400" height="673" scale="0.5" noninteractable="true" category="Decorative">
    <sprite texture="%ModDir%/map/slogan1.png" sourcerect="7,1573,1400,673" depth="0.97" premultiplyalpha="false" origin="0.5,0.5" />
  </OpDeco>
  <labelback nameidentifier="tsm_fog" subcategory="tsmmissions" identifier="tsm_fog" category="Decorative" allowattachitems="true" resizehorizontal="true" resizevertical="true" scale="1.0" noaitarget="true">
    <sprite texture="%ModDir%/map/fog.png" sourcerect="0,0,2000,1747" depth="0.999" premultiplyalpha="false" />
  </labelback>
  <OpDeco name="戎装机甲" identifier="tsm_rz1" subcategory="tsmmissions" nameidentifier="tsm_mech" width="155" height="293" scale="0.5" noninteractable="true" category="Decorative">
    <sprite texture="%ModDir%/map/rz.png" sourcerect="6,17,155,293" depth="0.97" premultiplyalpha="false" origin="0.5,0.5" />
  </OpDeco>
  <OpDeco name="戎装机甲" identifier="tsm_rz2" subcategory="tsmmissions" nameidentifier="tsm_mech" width="139" height="297" scale="0.5" noninteractable="true" category="Decorative">
    <sprite texture="%ModDir%/map/rz.png" sourcerect="191,17,139,297" depth="0.97" premultiplyalpha="false" origin="0.5,0.5" />
  </OpDeco>
  <OpDeco name="戎装机甲" identifier="tsm_rz3" subcategory="tsmmissions" nameidentifier="tsm_mech" width="153" height="293" scale="0.5" noninteractable="true" category="Decorative">
    <sprite texture="%ModDir%/map/rz.png" sourcerect="359,24,153,293" depth="0.97" premultiplyalpha="false" origin="0.5,0.5" />
  </OpDeco>
  <OpDeco name="魔女的下颚" identifier="tsm_mvdxe" subcategory="tsmmissions" nameidentifier="tsm_bossitem" width="153" height="214" scale="0.5" noninteractable="true" category="Decorative">
    <sprite texture="%ModDir%/map/bossitem.png" sourcerect="6,2,153,214" depth="0.97" premultiplyalpha="false" origin="0.5,0.5" />
  </OpDeco>
  <OpDeco name="雷龙的眼睛" identifier="tsm_lldyj" subcategory="tsmmissions" nameidentifier="tsm_bossitem" width="153" height="215" scale="0.5" noninteractable="true" category="Decorative">
    <sprite texture="%ModDir%/map/bossitem.png" sourcerect="165,2,153,215" depth="0.97" premultiplyalpha="false" origin="0.5,0.5" />
  </OpDeco>
  <OpDeco name="荒疫的毒腺" identifier="tsm_hyddx" subcategory="tsmmissions" nameidentifier="tsm_bossitem" width="153" height="220" scale="0.5" noninteractable="true" category="Decorative">
    <sprite texture="%ModDir%/map/bossitem.png" sourcerect="325,1,153,220" depth="0.97" premultiplyalpha="false" origin="0.5,0.5" />
  </OpDeco>
  <OpDeco name="大地悲鸣" identifier="tsm_ddbm" subcategory="tsmmissions" nameidentifier="tsm_bossitem" width="193" height="104" scale="0.5" noninteractable="true" category="Decorative">
    <sprite texture="%ModDir%/map/bossitem.png" sourcerect="22,272,193,104" depth="0.97" premultiplyalpha="false" origin="0.5,0.5" />
  </OpDeco>
  <OpDeco name="血肉装饰" identifier="tsm_eyi_ornamental1" subcategory="tsmmissions" nameidentifier="tsm_eyi_ornamental" width="251" height="255" scale="0.5" noninteractable="true" category="Decorative">
    <sprite texture="%ModDir%/map/eyi_ornamental1.png" sourcerect="0,0,251,255" depth="0.97" premultiplyalpha="false" origin="0.5,0.5" />
  </OpDeco>
  <OpDeco name="血肉装饰" identifier="tsm_eyi_ornamental2" subcategory="tsmmissions" nameidentifier="tsm_eyi_ornamental" width="269" height="282" scale="0.5" noninteractable="true" category="Decorative">
    <sprite texture="%ModDir%/map/eyi_ornamental2.png" sourcerect="0,0,269,282" depth="0.97" premultiplyalpha="false" origin="0.5,0.5" />
  </OpDeco>
  <OpDeco name="血肉装饰" identifier="tsm_eyi_ornamental3" subcategory="tsmmissions" nameidentifier="tsm_eyi_ornamental" width="844" height="721" scale="0.5" noninteractable="true" category="Decorative">
    <sprite texture="%ModDir%/map/eyi_ornamental3.png" sourcerect="0,0,844,721" depth="0.97" premultiplyalpha="false" origin="0.5,0.5" />
  </OpDeco>
  <OpDeco name="血肉装饰" identifier="tsm_eyi_ornamental4" subcategory="tsmmissions" nameidentifier="tsm_eyi_ornamental" width="865" height="529" scale="0.5" noninteractable="true" category="Decorative">
    <sprite texture="%ModDir%/map/eyi_ornamental4.png" sourcerect="6,0,859,529" depth="0.97" premultiplyalpha="false" origin="0.5,0.5" />
  </OpDeco>
  <OpDeco name="血肉装饰" identifier="tsm_eyi_ornamental5" subcategory="tsmmissions" nameidentifier="tsm_eyi_ornamental" width="493" height="314" scale="0.5" noninteractable="true" category="Decorative">
    <sprite texture="%ModDir%/map/eyi_ornamental5.png" sourcerect="2,5,489,287" depth="0.97" premultiplyalpha="false" origin="0.5,0.5" />
  </OpDeco>
  <OpDeco name="数字" identifier="tsm_eyi_7229" subcategory="tsmmissions" nameidentifier="tsm_eyi_ornamental" width="106" height="58" scale="0.5" noninteractable="true" category="Decorative">
    <sprite texture="%ModDir%/map/7229.png" sourcerect="2,2,102,54" depth="0.97" premultiplyalpha="false" origin="0.5,0.5" />
  </OpDeco>
  <OpDeco name="尸体" identifier="tsm_eyi_deadbody1" subcategory="tsmmissions" nameidentifier="tsm_eyi_ornamental" width="173" height="44" scale="0.5" noninteractable="true" category="Decorative">
    <sprite texture="%ModDir%/map/deadbody1.png" sourcerect="2,2,169,40" depth="0.97" premultiplyalpha="false" origin="0.5,0.5" />
  </OpDeco>
  <OpDeco name="尸体" identifier="tsm_eyi_deadbody2" subcategory="tsmmissions" nameidentifier="tsm_eyi_ornamental" width="173" height="44" scale="0.5" noninteractable="true" category="Decorative">
    <sprite texture="%ModDir%/map/deadbody2.png" sourcerect="2,2,169,40" depth="0.97" premultiplyalpha="false" origin="0.5,0.5" />
  </OpDeco>
  <OpDeco name="横幅" identifier="tsm_hf_1" subcategory="tsmmissions" nameidentifier="tsm_hf" width="908" height="114" scale="0.5" noninteractable="true" category="Decorative">
    <sprite texture="%ModDir%/map/横幅1.png" sourcerect="32,63,908,114" depth="0.97" premultiplyalpha="false" origin="0.5,0.5" />
  </OpDeco>
  <OpDeco name="横幅" identifier="tsm_hf_2" subcategory="tsmmissions" nameidentifier="tsm_hf" width="908" height="114" scale="0.5" noninteractable="true" category="Decorative">
    <sprite texture="%ModDir%/map/横幅2.png" sourcerect="32,63,908,114" depth="0.97" premultiplyalpha="false" origin="0.5,0.5" />
  </OpDeco>
  <OpDeco name="恶疫雕像" identifier="tsm_eyi_statues_1" subcategory="tsmmissions" nameidentifier="tsm_eyi_statues" width="161" height="145" scale="0.5" noninteractable="true" category="Decorative">
    <sprite texture="%ModDir%/item/eyi/eyi_item.png" sourcerect="0,171,161,145" depth="0.97" premultiplyalpha="false" origin="0.5,0.5" />
  </OpDeco>
</prefabs>